selenium_driver/__init__.py
selenium_driver/driver.py
selenium_driver-0.1.0.dist-info/licenses/LICENSE.MD
selenium_driver-0.1.0.dist-info/METADATA
selenium_driver-0.1.0.dist-info/WHEEL
selenium_driver-0.1.0.dist-info/top_level.txt
selenium_driver-0.1.0.dist-info/RECORD
